{
    "@odata.context": "/redfish/v1/$metadata#JsonSchemasFile/Members/$entity",
    "@odata.id": "/redfish/v1/JSONSchemas/HwNetworkHistoryUsageRate.v1_0_0",
    "@odata.type": "#JsonSchemaFile.v1_0_2.JsonSchemaFile",
    "Id": "HwNetworkHistoryUsageRate.v1_0_0",
    "Description": "HwNetworkHistoryUsageRate Schema File Location",
    "Name": "HwNetworkHistoryUsageRate Schema File",  
    "Languages": [
        "en"
    ],
    "Schema": "#HwNetworkHistoryUsageRate.v1_0_0.HwNetworkHistoryUsageRate",
    "Location": [
        {
            "Language": "en",
            "Uri": "/redfish/v1/SchemaStore/en/HwNetworkHistoryUsageRate.v1_0_0.json"
        }
    ]  
}