{
    "AllowedOperation" : 1,
    "RedfishObject" :
    {
        "@odata.context": "/redfish/v1/$metadata#Chassis/Members/1/Power/PowerHistoryData/$entity",
        "@odata.id": "/redfish/v1/Chassis/1/Power/PowerHistoryData",
        "@odata.type": "#HwPowerHistoryData.v1_0_0.HwPowerHistoryData",
        "Id":"PowerHistoryData",
        "Name": "Power History Data",
        "Description": "Power History Data",
        "Data": [
            {
                "Time": "2018/06/26 10:23:04",
                "PowerWatts": 0,
                "PowerAverageWatts": 0,
                "PowerPeakWatts": 0 
            }
        ]
    }       
}