{
    "$schema": "http://redfish.dmtf.org/schemas/v1/redfish-schema.v1_1_0.json",
    "title": "#DiceCert.DiceCert",
    "$ref": "#/definitions/DiceCert",
    "definitions": {
        "DiceCert": {
            "anyOf": [
                {
                    "$ref": "http://redfish.dmtf.org/schemas/v1/odata.4.0.0.json#/definitions/idRef"
                },
                {
                    "$ref": "/redfish/v1/SchemaStore/en/Dicecert.v1_0_0.json#/definitions/DiceCert"
                }
            ]
        }
    },
    "copyright": "Copyright © Huawei Technologies Co., Ltd. 2021. All rights reserved."
}
