<?xml version="1.0" encoding="UTF-8"?>
<!-- lang_dxxxxxxxx_str或lang_sxxxxxxxx_str中的事件码xxxxxxxx如果有英文字母时，必须用大写的英文字母 -->
<LANG>
    <!--告警语言版本号和BMC版本号保持一致，比如 5.50 B007版本，分别填写语言文件中MAJOR_VERSION=5 MINOR_VERSION=50 AUX_VERSION=7
		该版本号现由脚本 update_event_lang_template_version.sh自动刷新，与platform_v5.xml中的版本号保持一致-->
	<MAJOR_VERSION>6</MAJOR_VERSION>
	<MINOR_VERSION>50</MINOR_VERSION>
	<AUX_VERSION>10</AUX_VERSION>
	
	<!-- 英文 -->
	<LanguageSet NAME="en">
	    <!-- 英文描述 -->
		<EventDescription>
		</EventDescription>
		
		<!-- 英文建议 -->
		<EventSuggestion>
			<!-- CPU 事件处理建议 -->
			<Item NAME="lang_s00000003_str">1. Check for high temperature alarm of air inlet or outlet.@#AB;2. Check for fan alarms.@#AB;3. Check whether the air duct is installed.@#AB;4. Check whether the CPU heat sink or liquid cooling device is correctly installed.@#AB;@#AB;5. Replace the mainboard.</Item>
			<Item NAME="lang_s01000003_str">1. Remove the DIMMs connected to the CPU and check if the alarm is caused by the DIMMs. If yes, replace the faulty DIMMs. If no, replace the mainboard.</Item>
			<Item NAME="lang_s01000005_str">1. Remove the DIMMs connected to the CPU and check if the alarm is caused by the DIMMs. If yes, replace the faulty DIMMs. If no, replace the mainboard.</Item>
			<Item NAME="lang_s01000007_str">1. Remove the DIMMs connected to the CPU and check if the alarm is caused by the DIMMs. If yes, replace the faulty DIMMs. If no, replace the mainboard.</Item>
			<Item NAME="lang_s01000009_str">1. Remove the DIMMs connected to the CPU and check if the alarm is caused by the DIMMs. If yes, replace the faulty DIMMs. If no, replace the mainboard.</Item>
			<Item NAME="lang_s0000001F_str">1. Replace the mainboard</Item>
			<Item NAME="lang_s02000025_str">1. Check whether the hard disk is properly inserted.@#AB;2. Replace the NVMe cable or SAS cable.@#AB;3. Replace the hard disk backplane or transfer card.@#AB;4. Replace the mainboard.</Item>
			<Item NAME="lang_s2800001F_str">1. Power off the server and check whether there is damage or poor contact between the component and its slot.@#AB;2. Replace the mainboard.</Item>
			<Item NAME="lang_s00000073_str">1. Check whether CPU is installed.@#AB;2 .replace the mainboard.</Item>
			<Item NAME="lang_s0000000F_str">1. Check for high temperature alarm of air inlet or outlet.@#AB;2. Check for fan alarms.@#AB;3. Check whether the air duct is installed.@#AB;4. Check whether the CPU heat sink or liquid cooling device is correctly installed.@#AB;5. Replace the mainboard.</Item>
			<Item NAME="lang_s00000011_str">1. Replace the mainboard.</Item>
			<Item NAME="lang_s0000000B_str">1. Replace the mainboard.</Item>
			<Item NAME="lang_s0000000D_str">1. Replace the mainboard.</Item>
			<Item NAME="lang_s00000013_str">1. Check whether all CPU models are the same.@#AB;2. Replace the mainboard.</Item>
			<Item NAME="lang_s00000065_str">1. Replace the mainboard.</Item><!-- 维护日志，不需加换行符 -->
			<Item NAME="lang_s00000067_str">1. Replace the mainboard.</Item>
		</EventSuggestion>
	
       <!-- 英文影响 -->
        <EventEffect>
        </EventEffect>
        <!-- 英文原因 -->       		
        <EventCause>
		</EventCause>

	</LanguageSet>
	
	<!-- 中文 -->
	<LanguageSet NAME="zh">
	    <!-- 中文描述 -->
		<EventDescription>
        </EventDescription>
		
		<!-- 中文建议 -->
		<EventSuggestion>
			<Item NAME="lang_s00000003_str">1、检查服务器是否同时存在进风口/出风口高温告警。@#AB;2、检查服务器是否同时存在风扇告警。@#AB;3、检查服务器是否已安装导风罩。@#AB;4、检查是否正确安装CPU散热器或液冷装置。@#AB;5、更换主板。</Item>
			<Item NAME="lang_s01000003_str">1、拔掉该CPU下挂内存，确定告警是否由内存引起。如果告警由内存产生，更换内存。如果告警非内存产生，更换主板。</Item>
			<Item NAME="lang_s01000005_str">1、拔掉该CPU下挂内存，确定告警是否由内存引起。如果告警由内存产生，更换内存。如果告警非内存产生，更换主板。</Item>
			<Item NAME="lang_s01000007_str">1、拔掉该CPU下挂内存，确定告警是否由内存引起。如果告警由内存产生，更换内存。如果告警非内存产生，更换主板。</Item>
			<Item NAME="lang_s01000009_str">1、拔掉该CPU下挂内存，确定告警是否由内存引起。如果告警由内存产生，更换内存。如果告警非内存产生，更换主板。</Item>
			<Item NAME="lang_s0000001F_str">1、更换主板</Item>
			<Item NAME="lang_s02000025_str">1、检查硬盘是否插好。@#AB;2、更换NVMe线缆或者SAS线缆。@#AB;3、更换硬盘背板或转接卡。@#AB;4、更换主板。</Item>
			<Item NAME="lang_s2800001F_str">1、下电后检查该部件与其插槽是否存在损坏或接触不良现象。@#AB;2、更换主板。</Item>
			<Item NAME="lang_s00000073_str">1、检测CPU是否在位。@#AB;2、更换主板。</Item>
			<Item NAME="lang_s0000000F_str">1、检查服务器是否同时存在进风口/出风口高温告警。@#AB;2、检查服务器是否同时存在风扇告警。@#AB;3、检查服务器是否已安装导风罩。@#AB;4、检查是否正确安装CPU散热器或液冷装置。@#AB;5、更换主板。</Item>
			<Item NAME="lang_s00000011_str">1、更换主板。</Item>
			<Item NAME="lang_s0000000B_str">1、更换主板。</Item>
			<Item NAME="lang_s0000000D_str">1、更换主板。</Item>
			<Item NAME="lang_s00000013_str">1、检查CPU型号是否一致。@#AB;2、更换主板。</Item>
			<Item NAME="lang_s00000065_str">1、更换主板。</Item>
			<Item NAME="lang_s00000067_str">1、更换主板。</Item>
		</EventSuggestion>
	    <!-- 中文影响 -->
        <EventEffect>
        </EventEffect>
        <!-- 中文原因 -->       		
        <EventCause>
		</EventCause>
	</LanguageSet>
	
	
</LANG>
