{
    "AllowedOperation": 5,
    "RedfishObject": {
        "@odata.context": "/redfish/v1/$metadata#Systems/Members/1/Bios/$entity",
        "@odata.id": "/redfish/v1/Systems/1/Bios",
        "@odata.type": "#Bios.v1_0_0.Bios",
        "Id": "Bios",
        "Name": "BIOS Configuration Current Settings",
        "AttributeRegistry": "BiosAttributeRegistry.1.0.0",
        "Attributes": {
        },
        "@Redfish.Settings": {
            "@odata.type": "#Settings.v1_0_2.Settings",
            "ETag": "9234ac83b9700123cc32",
            "Messages": [
                {
                    "MessageId": "Base.1.0.SettingsFailed",
                    "RelatedProperties": [
                        "#/Attributes/ProcTurboMode"
                    ]
                }
            ],
            "SettingsObject": {
                "@odata.id": "/redfish/v1/Systems/1/Bios/Settings"
            },
            "Time": "2016-03-07 14:44.30-05:00"
        },
        "Actions": {
            "#Bios.ResetBios": {
                "target": "/redfish/v1/Systems/1/Bios/Actions/Bios.ResetBios",
                "@Redfish.ActionInfo": "/redfish/v1/Systems/1/Bios/ResetBiosActionInfo"
            },
            "#Bios.ChangePassword": {
                "target": "/redfish/v1/Systems/1/Bios/Actions/Bios.ChangePassword",
                "@Redfish.ActionInfo": "/redfish/v1/Systems/1/Bios/ChangePasswordActionInfo"
            }
        },
        "Oem": {
        },
        "PolicyConfig": {
            "@odata.id": "/redfish/v1/Systems/1/Bios/PolicyConfig"
        }
    }
}