 {
       "AllowedOperation": 1,
	   "RedfishObject": {
       "@odata.context": "/redfish/v1/$metadata#Managers/Members/SLOT_ID/VirtualMedia/$entity",
       "@odata.id": "/redfish/v1/Managers/SLOT_ID/VirtualMedia",
       "@odata.type": "#VirtualMediaCollection.VirtualMediaCollection",
       "Name": "Virtual Media Services",
       "Description": "Virtual Media Services Settings",
       "Members@odata.count": 2,
       "Members": [
          {
              "@odata.id": "/redfish/v1/Managers/SLOT_ID/VirtualMedia/CD"
          },
		  {
              "@odata.id": "/redfish/v1/Managers/SLOT_ID/VirtualMedia/USBStick"
          },
		  {
              "@odata.id": "/redfish/v1/Managers/SLOT_ID/VirtualMedia/iBMAUSBStick"
          }
      ]

      }
    }
